fluss_next/__init__.py
fluss_next/arkitekt.py
fluss_next/errors.py
fluss_next/fluss.py
fluss_next/funcs.py
fluss_next/py.typed
fluss_next/rath.py
fluss_next/rekuest.py
fluss_next/scalars.py
fluss_next/structures.py
fluss_next/traits.py
fluss_next/api/__init__.py
fluss_next/api/project.json
fluss_next/api/schema.graphql
fluss_next/api/schema.py
fluss_next-0.7.0.dist-info/METADATA
fluss_next-0.7.0.dist-info/WHEEL
fluss_next-0.7.0.dist-info/RECORD
