Metadata-Version: 2.4
Name: fluss-next
Version: 0.7.0
Summary: the next generation of Fluss, a Python library for workflow design
Author-email: jhnnsrs <jhnnsrs@gmail.com>
License-Expression: GPL-3.0-or-later
Requires-Python: <4.0,>=3.11
Requires-Dist: rath>=3.5.1
Requires-Dist: websockets>=15.0.1
